maze_generator_and_solver/__init__.py
maze_generator_and_solver/main.py
maze_generator_and_solver-0.0.7.dist-info/METADATA
maze_generator_and_solver-0.0.7.dist-info/WHEEL
maze_generator_and_solver-0.0.7.dist-info/licenses/LICENSE
maze_generator_and_solver-0.0.7.dist-info/RECORD
