Metadata-Version: 2.1
Name: maze_generator_and_solver
Version: 0.0.7
Summary: Generate maze using randomized DFS and Solve it using Path Finding algorithms
Project-URL: Bug Tracker, https://github.com/0-harshit-0/maze/issues
Author-email: Harshit <harshitw3b@gmail.com>
License-File: LICENSE
Classifier: License :: OSI Approved :: GNU General Public License v3 (GPLv3)
Classifier: Operating System :: OS Independent
Classifier: Programming Language :: Python :: 3
Requires-Python: >=3.7
